LICENCE.txt
MANIFEST.in
README.rst
setup.py
emencia_cms_snippet.egg-info/PKG-INFO
emencia_cms_snippet.egg-info/SOURCES.txt
emencia_cms_snippet.egg-info/dependency_links.txt
emencia_cms_snippet.egg-info/not-zip-safe
emencia_cms_snippet.egg-info/requires.txt
emencia_cms_snippet.egg-info/top_level.txt
snippet/__init__.py
snippet/admin.py
snippet/cms_plugins.py
snippet/models.py
snippet/migrations/0001_initial.py
snippet/migrations/0002_publisher.py
snippet/migrations/0003_table_rename.py
snippet/migrations/0004_publisher2.py
snippet/migrations/0005_template_added.py
snippet/migrations/0006_auto__add_field_snippet_slug.py
snippet/migrations/0007_fill_slugs.py
snippet/migrations/0008_auto__add_unique_snippet_slug.py
snippet/migrations/__init__.py
snippet/static/djangocodemirror/snippet_buttons.js
snippet/templates/cms/plugins/snippet.html
snippet/templatetags/__init__.py
snippet/templatetags/snippet_tags.py