Metadata-Version: 1.0
Name: emencia-cms-snippet
Version: 2.4.0
Summary: 
